{
  "seo": {
    "title": "Meyad-Leyad",
    "description": ""
  },

  "header": {
    "newAd": "New ad",
    "amEhad": "To website: Am Echad",
    "meyadLeyad": "Immediately"
  },
  "switcher": {
    "need": "Need Help",
    "dontNeed": "Offering Help"
  },
  "filters": {
    "housing": "Housing",
    "food": "Food",
    "animals": "Animals",
    "children": "Children",
    "mental": "Mental Assistance",
    "tramps": "Rides",
    "transportation": "Transports",
    "clothing": "Clothing",
    "other": "Other"
  },
  "subFilters": {
    "onePerson": "1 Person",
    "twoPeople": "1-3 People",
    "threePeople": "3-10 People",
    "fourPeople": "More than 10 People",
    "oneAnimal": "1 Animal",
    "twoAnimals": "2 Animals",
    "threeAnimals": "3+ Animals"
  },
  "filtersText": {
    "housingText": "Providing housing solutions",
    "foodText": "Help in finding food, food delivery",
    "animalsText": "Finding shelter and medical assistance for animals",
    "childrenText": "Finding food for babies and breast milk",
    "mentalText": "Mental assistance for those in need",
    "trampsText": "Search for transport, travel companion, movement within the country",
    "transportationText": "Help in transporting goods, donations",
    "clothingText": "Donation of items",
    "otherText": ""
  },
  "post": {
    "total": "Total",
    "posts": "Posts",
    "military": "Military",
    "civil": "Civilian",
    "copy": "Copy",
    "open": "Open",
    "close": "Close",
    "urgency": "Urgency",
    "oneUrgent": "1 Hour",
    "twoUrgent": "12 Hours",
    "threeUrgent": "24 Hours",
    "fourUrgent": "Not urgent",
    "copied": "The post was copied to the clipboard"
  },
  "form": {
    "title": "Choose the category in which help is needed",
    "toHelpTitle": "Choose the category in which you want to help",
    "fName": "Ad Name",
    "area": "Area",
    "phone": "Phone",
    "military": "Military",
    "civil": "Civilian",
    "urgency": "Urgency",
    "oneUrgent": "1 Hour",
    "twoUrgent": "12 Hours",
    "threeUrgent": "24 Hours",
    "fourUrgent": "Not urgent",
    "textArea": "Description",
    "textPlaceholderNeed": "What do you need help with?",
    "textPlaceholder": "How can you help?",
    "textFooterNeed": "Write briefly and clearly what you need help with",
    "textFooter": "Write briefly and clearly how you can help",
    "submit": "Publish",
    "mustBeFilled": "Must be filled",
    "tooLong": "The value is too long"
  },
  "misc": {
    "all": "Whole country",
    "inTotal": "Ads in total",
    "loadMore": "Load More",
    "noMore": "No More Ads",
    "jerusalem": "Jerusalem",
    "telAviv": "Tel Aviv",
    "north": "North",
    "haifa": "Haifa",
    "center": "Center",
    "south": "South",
    "yehuda": "Judea and Samaria",
    "search": "Search",
    "choose": "Choose Area"
  }
}
